seokbong_mul/__init__.py
seokbong_mul/mul.py
seokbong_mul-1.0.2.dist-info/METADATA
seokbong_mul-1.0.2.dist-info/WHEEL
seokbong_mul-1.0.2.dist-info/entry_points.txt
seokbong_mul-1.0.2.dist-info/top_level.txt
seokbong_mul-1.0.2.dist-info/RECORD
