Metadata-Version: 2.1
Name: seokbong_mul
Version: 1.0.2
Summary: Default template for PDM package
Author-email: Seokxkyu <kyuseok000@gmail.com>
License: MIT
Requires-Python: >=3.9
